pytest_mark_manage/__init__.py
pytest_mark_manage/__version__.py
pytest_mark_manage/conf.py
pytest_mark_manage/plugin.py
pytest_mark_manage/skipif.py
pytest_mark_manage-2024.8.15.dist-info/METADATA
pytest_mark_manage-2024.8.15.dist-info/WHEEL
pytest_mark_manage-2024.8.15.dist-info/entry_points.txt
pytest_mark_manage-2024.8.15.dist-info/licenses/LICENSE
pytest_mark_manage-2024.8.15.dist-info/RECORD
