Metadata-Version: 2.1
Name: pytest-mark-manage
Version: 2024.8.15
Summary: 用例标签化管理
Author-email: mikigo <huangmingqiang@uniontech.com>
License: GPL2.0
License-File: LICENSE
Requires-Python: >=3.7
Requires-Dist: funnylog2
Requires-Dist: pytest
